Metadata-Version: 1.0
Name: test-gaussian-binomial-Udacity-project
Version: 0.1
Summary: Gaussian and Binomial distributions
Home-page: UNKNOWN
Author: felixquinihildebet
Author-email: UNKNOWN
License: UNKNOWN
Platform: UNKNOWN
